mlogic/__init__.py
mlogic/utils/__init__.py
mlogic/utils/stats.py
mlogic-0.1.dist-info/LICENSE
mlogic-0.1.dist-info/METADATA
mlogic-0.1.dist-info/WHEEL
mlogic-0.1.dist-info/top_level.txt
mlogic-0.1.dist-info/RECORD
