Metadata-Version: 2.1
Name: mlogic
Version: 0.1
Summary: Useful functions for machine learning
Home-page: UNKNOWN
Author: Brendon Lin
Author-email: brendon.lin@outlook.com
License: UNKNOWN
Platform: UNKNOWN
Requires-Dist: numpy (>=1.18.4)
Requires-Dist: pandas (>=1.0.3)
Requires-Dist: scikit-learn (>=0.23.1)
Requires-Dist: scipy (>=1.4.1)
